oddsummer_lotto/__init__.py
oddsummer_lotto/lotto.py
oddsummer_lotto-0.1.0.dist-info/METADATA
oddsummer_lotto-0.1.0.dist-info/WHEEL
oddsummer_lotto-0.1.0.dist-info/top_level.txt
oddsummer_lotto-0.1.0.dist-info/RECORD
