Metadata-Version: 2.1
Name: oddsummer_lotto
Version: 0.1.0
Summary: Default template for PDM package
Author-email: oddsummer56 <oddsummer56@gmail.com>
License: MIT
Requires-Python: >=3.9
